mnist_ae/__init__.py
mnist_ae/_modidx.py
mnist_ae/core.py
mnist_ae/mnist_training.py
mnist_ae-0.0.7.dist-info/licenses/LICENSE
mnist_ae-0.0.7.dist-info/METADATA
mnist_ae-0.0.7.dist-info/WHEEL
mnist_ae-0.0.7.dist-info/entry_points.txt
mnist_ae-0.0.7.dist-info/top_level.txt
mnist_ae-0.0.7.dist-info/RECORD
