Metadata-Version: 2.4
Name: mnist_ae
Version: 0.0.7
Summary: MNIST auto-encoder
Home-page: https://github.com/ofgarzon2662/mnist_ae
Author: Fernando Garzon
Author-email: of.garzon2662@uniandes.edu.co
License: Apache Software License 2.0
Keywords: nbdev jupyter notebook python
Classifier: Development Status :: 4 - Beta
Classifier: Intended Audience :: Developers
Classifier: Natural Language :: English
Classifier: Programming Language :: Python :: 3.9
Classifier: Programming Language :: Python :: 3.10
Classifier: Programming Language :: Python :: 3.11
Classifier: Programming Language :: Python :: 3.12
Classifier: License :: OSI Approved :: Apache Software License
Requires-Python: >=3.9
License-File: LICENSE
Requires-Dist: torch
Requires-Dist: torchvision
Provides-Extra: dev
Requires-Dist: jupyter; extra == "dev"
Requires-Dist: matplotlib; extra == "dev"
Requires-Dist: nbdev; extra == "dev"
Requires-Dist: black; extra == "dev"
Dynamic: author
Dynamic: author-email
Dynamic: classifier
Dynamic: description
Dynamic: description-content-type
Dynamic: home-page
Dynamic: keywords
Dynamic: license
Dynamic: license-file
Dynamic: provides-extra
Dynamic: requires-dist
Dynamic: requires-python
Dynamic: summary
